<?xml version="1.0"?>
<!DOCTYPE hibernate-mapping PUBLIC "-//Hibernate/Hibernate Mapping DTD 3.0//EN"
"http://www.hibernate.org/dtd/hibernate-mapping-3.0.dtd">
<!-- Generated 06-nov-2017 19:58:31 by Hibernate Tools 4.3.5.Final -->
<hibernate-mapping>
    <class name="es.curso.bean.Pedidos" table="pedidos" catalog="empresa3" optimistic-lock="version">
        <id name="idpedido" type="int">
            <column name="idpedido" />
            <generator class="assigned" />
        </id>
        <many-to-one name="clientes" class="es.curso.bean.Clientes" fetch="select">
            <column name="idcliente" length="10" not-null="true" />
        </many-to-one>
        <many-to-one name="empleados" class="es.curso.bean.Empleados" fetch="select">
            <column name="idempleado" not-null="true" />
        </many-to-one>
        <many-to-one name="empresasenvios" class="es.curso.bean.Empresasenvios" fetch="select">
            <column name="idempresaenvio" not-null="true" />
        </many-to-one>
        <property name="importe" type="java.lang.Float">
            <column name="importe" precision="12" scale="0" />
        </property>
        <property name="pais" type="string">
            <column name="pais" length="50" />
        </property>
        <set name="detallespedidos" table="detallespedido" inverse="true" lazy="true" fetch="select">
            <key>
                <column name="idpedido" not-null="true" />
            </key>
            <one-to-many class="es.curso.bean.Detallespedido" />
        </set>
    </class>
</hibernate-mapping>
